edc_adherence/__init__.py
edc_adherence/apps.py
edc_adherence/choices.py
edc_adherence/form_validator_mixin.py
edc_adherence/list_data.py
edc_adherence/migrations/0001_initial.py
edc_adherence/migrations/0002_nonadherencereasons_plural_name.py
edc_adherence/migrations/0003_nonadherencereasons_extra_value.py
edc_adherence/migrations/0004_alter_nonadherencereasons_options_and_more.py
edc_adherence/migrations/__init__.py
edc_adherence/model_admin_mixin.py
edc_adherence/model_form_mixin.py
edc_adherence/model_mixins.py
edc_adherence/models.py
edc_adherence/templates/edc_adherence/missed_medication_fieldset_description.html
edc_adherence/templates/edc_adherence/visual_score_fieldset_description.html
edc_adherence/tests/__init__.py
edc_adherence/tests/admin.py
edc_adherence/tests/consents.py
edc_adherence/tests/forms.py
edc_adherence/tests/holidays.csv
edc_adherence/tests/models.py
edc_adherence/tests/tests/__init__.py
edc_adherence/tests/tests/test_adherence.py
edc_adherence/tests/urls.py
edc_adherence/tests/visit_schedules.py
edc_adherence-1.2.0.dist-info/licenses/LICENSE
edc_adherence-1.2.0.dist-info/WHEEL
edc_adherence-1.2.0.dist-info/METADATA
edc_adherence-1.2.0.dist-info/RECORD
