Metadata-Version: 2.4
Name: edc-adherence
Version: 1.2.0
Summary: Classes to manage adherence in clinicedc/edc projects
Keywords: django,clinicedc,edc,clinical trials,research,data management,esource,adherence
Author: Erik van Widenfelt, Jonathan Willitts
Author-email: Erik van Widenfelt <ew2789@gmail.com>, Jonathan Willitts <j.willitts@ucl.ac.uk>
License-Expression: GPL-3.0-or-later
License-File: LICENSE
Classifier: Environment :: Web Environment
Classifier: Framework :: Django
Classifier: Framework :: Django :: 5.2
Classifier: Development Status :: 5 - Production/Stable
Classifier: Intended Audience :: Developers
Classifier: Intended Audience :: Science/Research
Classifier: Operating System :: OS Independent
Classifier: Programming Language :: Python :: 3.12
Classifier: Programming Language :: Python :: 3.13
Maintainer: Erik van Widenfelt
Maintainer-email: Erik van Widenfelt <ew2789@gmail.com>
Requires-Python: >=3.12
Project-URL: Changelog, https://github.com/clinicedc/edc-adherence/blob/main/CHANGES
Project-URL: Documentation, https://github.com/clinicedc/edc-adherence/blob/main/README.rst
Project-URL: Homepage, https://github.com/clinicedc/edc-adherence
Project-URL: Repository, https://github.com/clinicedc/edc-adherence.git
